quicfire_tools/__init__.py
quicfire_tools/ignitions.py
quicfire_tools/inputs.py
quicfire_tools/outputs.py
quicfire_tools/topography.py
quicfire_tools/utils.py
quicfire_tools/data/documentation/IgnitionType.json
quicfire_tools/data/documentation/QFire_Advanced_User_Inputs.inp.json
quicfire_tools/data/documentation/QFire_Bldg_Advanced_User_Inputs.inp.json
quicfire_tools/data/documentation/QFire_Plume_Advanced_User_Inputs.inp.json
quicfire_tools/data/documentation/QP_buildout.inp.json
quicfire_tools/data/documentation/QUIC_fire.inp.json
quicfire_tools/data/documentation/QU_TopoInputs.inp.json
quicfire_tools/data/documentation/QU_buildings.inp.json
quicfire_tools/data/documentation/QU_fileoptions.inp.json
quicfire_tools/data/documentation/QU_metparams.inp.json
quicfire_tools/data/documentation/QU_movingcoords.inp.json
quicfire_tools/data/documentation/QU_simparams.inp.json
quicfire_tools/data/documentation/Runtime_Advanced_User_Inputs.inp.json
quicfire_tools/data/documentation/TopoType.json
quicfire_tools/data/documentation/gridlist.json
quicfire_tools/data/documentation/rasterorigin.txt.json
quicfire_tools/data/documentation/sensor1.inp.json
quicfire_tools/data/outputs/outputs.json
quicfire_tools/data/templates/v5/QFire_Advanced_User_Inputs.inp
quicfire_tools/data/templates/v5/QFire_Bldg_Advanced_User_Inputs.inp
quicfire_tools/data/templates/v5/QFire_Plume_Advanced_User_Inputs.inp
quicfire_tools/data/templates/v5/QP_buildout.inp
quicfire_tools/data/templates/v5/QUIC_fire.inp
quicfire_tools/data/templates/v5/QU_TopoInputs.inp
quicfire_tools/data/templates/v5/QU_buildings.inp
quicfire_tools/data/templates/v5/QU_fileoptions.inp
quicfire_tools/data/templates/v5/QU_landuse.inp
quicfire_tools/data/templates/v5/QU_metparams.inp
quicfire_tools/data/templates/v5/QU_movingcoords.inp
quicfire_tools/data/templates/v5/QU_simparams.inp
quicfire_tools/data/templates/v5/Runtime_Advanced_User_Inputs.inp
quicfire_tools/data/templates/v5/gridlist
quicfire_tools-0.11.0.dist-info/licenses/LICENSE
quicfire_tools-0.11.0.dist-info/METADATA
quicfire_tools-0.11.0.dist-info/WHEEL
quicfire_tools-0.11.0.dist-info/top_level.txt
quicfire_tools-0.11.0.dist-info/RECORD
