Metadata-Version: 2.4
Name: quicfire-tools
Version: 0.11.0
Summary: Input and output management tools for the QUIC-Fire fire model
Author: Anthony Marcozzi, Niko Tutland, Zachary Cope
License-Expression: MIT
Project-URL: Homepage, https://github.com/silvxlabs/quicfire-tools
Project-URL: Bug Tracker, https://github.com/silvxlabs/quicfire-tools/issues
Classifier: Intended Audience :: Developers
Classifier: Intended Audience :: Science/Research
Classifier: Operating System :: OS Independent
Classifier: Programming Language :: Python :: 3
Classifier: Programming Language :: Python :: 3.9
Classifier: Programming Language :: Python :: 3.10
Classifier: Programming Language :: Python :: 3.11
Classifier: Programming Language :: Python :: 3.12
Classifier: Topic :: Scientific/Engineering
Requires-Python: >=3.9
License-File: LICENSE
Requires-Dist: dask
Requires-Dist: dask-expr
Requires-Dist: netCDF4
Requires-Dist: numpy
Requires-Dist: pandas
Requires-Dist: pydantic>=2
Requires-Dist: pyproj
Requires-Dist: scipy
Requires-Dist: zarr
Dynamic: license-file
